vivarium/__init__.py
vivarium/actor/__init__.py
vivarium/actor/actor.py
vivarium/actor/boot.py
vivarium/actor/control.py
vivarium/actor/emitter.py
vivarium/actor/event.py
vivarium/actor/filepath.py
vivarium/actor/inner.py
vivarium/actor/outer.py
vivarium/actor/process.py
vivarium/actor/shepherd.py
vivarium/actor/stub.py
vivarium/analysis/__init__.py
vivarium/analysis/analysis.py
vivarium/analysis/analyze_compartment.py
vivarium/analysis/location_trace.py
vivarium/analysis/motor.py
vivarium/analysis/multigen_compartment.py
vivarium/analysis/run_analysis.py
vivarium/analysis/snapshots.py
vivarium/analysis/topology.py
vivarium/composites/PMF_chemotaxis.py
vivarium/composites/__init__.py
vivarium/composites/growth_division.py
vivarium/composites/iFBA.py
vivarium/composites/kinetic_FBA.py
vivarium/composites/simple_chemotaxis.py
vivarium/data/__init__.py
vivarium/data/helper.py
vivarium/data/knowledge_base.py
vivarium/data/spreadsheets.py
vivarium/data/flat/__init__.py
vivarium/data/flat/covert2002_GLC_G6P_flux_bounds.tsv
vivarium/data/flat/covert2002_ecoli_metabolism_met_mw.tsv
vivarium/data/flat/covert2002_exchange_fluxes.tsv
vivarium/data/flat/covert2002_maintenance_biomass_fluxes.tsv
vivarium/data/flat/covert2002_reactions.tsv
vivarium/data/flat/covert2002_regulatory_proteins.tsv
vivarium/data/flat/covert2002_transport.tsv
vivarium/data/flat/lookup_conc_minimal.tsv
vivarium/data/flat/lookup_conc_minimal_minus_oxygen.tsv
vivarium/data/flat/lookup_conc_minimal_plus_amino_acids.tsv
vivarium/data/flat/lookup_flux_minimal.tsv
vivarium/data/flat/lookup_flux_minimal_minus_oxygen.tsv
vivarium/data/flat/lookup_flux_minimal_plus_amino_acids.tsv
vivarium/data/flat/media_recipes.tsv
vivarium/data/flat/timelines_def.tsv
vivarium/data/flat/wcEcoli_biomass.tsv
vivarium/data/flat/wcEcoli_complexationReactions.tsv
vivarium/data/flat/wcEcoli_environment_molecules.tsv
vivarium/data/flat/wcEcoli_proteins.tsv
vivarium/data/flat/wcEcoli_reactions.tsv
wholecell_vivarium-0.0.40.dist-info/LICENSE
wholecell_vivarium-0.0.40.dist-info/METADATA
wholecell_vivarium-0.0.40.dist-info/WHEEL
wholecell_vivarium-0.0.40.dist-info/entry_points.txt
wholecell_vivarium-0.0.40.dist-info/top_level.txt
wholecell_vivarium-0.0.40.dist-info/RECORD
