Metadata-Version: 2.1
Name: wholecell-vivarium
Version: 0.0.40
Summary: UNKNOWN
Home-page: https://github.com/CovertLab/vivarium
Author: Eran Agmon, Ryan Spangler
Author-email: eagmon@stanford.edu, spanglry@stanford.edu
License: MIT
Platform: UNKNOWN
Requires-Dist: Arpeggio (==1.9.1)
Requires-Dist: cffi (==1.13.2)
Requires-Dist: cobra (==0.17.1)
Requires-Dist: confluent-kafka (==0.11.5)
Requires-Dist: matplotlib (==2.2.2)
Requires-Dist: numpy (==1.14.6)
Requires-Dist: parsimonious (==0.8.1)
Requires-Dist: Pint (==0.9)
Requires-Dist: pygame (==1.9.6)
Requires-Dist: pymongo (==3.6.1)
Requires-Dist: pymunk (==5.6.0)
Requires-Dist: pytest (==4.6.5)
Requires-Dist: pytest-benchmark (==3.2.2)
Requires-Dist: scipy (==1.0.1)
Requires-Dist: scs (==2.0.2)
Requires-Dist: stochastic-arrow (==0.2.0)
Requires-Dist: swiglpk (==1.4.4)
